{"nodes": [{"id": "d_all_web_project_videoprotfoly_components_sections_aboutme_tsx", "label": "AboutMe.tsx", "file_type": "code", "source_file": "D:\\All Web project\\videoprotfoly\\components\\sections\\AboutMe.tsx", "source_location": "L1"}, {"id": "sections_aboutme_aboutmeprops", "label": "AboutMeProps", "file_type": "code", "source_file": "D:\\All Web project\\videoprotfoly\\components\\sections\\AboutMe.tsx", "source_location": "L161"}, {"id": "sections_aboutme_githubicon", "label": "GithubIcon()", "file_type": "code", "source_file": "D:\\All Web project\\videoprotfoly\\components\\sections\\AboutMe.tsx", "source_location": "L167"}, {"id": "sections_aboutme_linkedinicon", "label": "LinkedinIcon()", "file_type": "code", "source_file": "D:\\All Web project\\videoprotfoly\\components\\sections\\AboutMe.tsx", "source_location": "L181"}, {"id": "sections_aboutme_instagramicon", "label": "InstagramIcon()", "file_type": "code", "source_file": "D:\\All Web project\\videoprotfoly\\components\\sections\\AboutMe.tsx", "source_location": "L197"}, {"id": "sections_aboutme_youtubeicon", "label": "YoutubeIcon()", "file_type": "code", "source_file": "D:\\All Web project\\videoprotfoly\\components\\sections\\AboutMe.tsx", "source_location": "L213"}, {"id": "sections_aboutme_aboutme", "label": "AboutMe()", "file_type": "code", "source_file": "D:\\All Web project\\videoprotfoly\\components\\sections\\AboutMe.tsx", "source_location": "L228"}], "edges": [{"source": "d_all_web_project_videoprotfoly_components_sections_aboutme_tsx", "target": "react", "relation": "imports_from", "context": "import", "confidence": "EXTRACTED", "source_file": "D:\\All Web project\\videoprotfoly\\components\\sections\\AboutMe.tsx", "source_location": "L157", "weight": 1.0}, {"source": "d_all_web_project_videoprotfoly_components_sections_aboutme_tsx", "target": "link", "relation": "imports_from", "context": "import", "confidence": "EXTRACTED", "source_file": "D:\\All Web project\\videoprotfoly\\components\\sections\\AboutMe.tsx", "source_location": "L158", "weight": 1.0}, {"source": "d_all_web_project_videoprotfoly_components_sections_aboutme_tsx", "target": "d_all_web_project_videoprotfoly_hooks_useabout_ts", "relation": "imports_from", "context": "import", "confidence": "EXTRACTED", "source_file": "D:\\All Web project\\videoprotfoly\\components\\sections\\AboutMe.tsx", "source_location": "L159", "weight": 1.0}, {"source": "d_all_web_project_videoprotfoly_components_sections_aboutme_tsx", "target": "hooks_useabout_aboutdataresponse", "relation": "imports", "context": "import", "confidence": "EXTRACTED", "source_file": "D:\\All Web project\\videoprotfoly\\components\\sections\\AboutMe.tsx", "source_location": "L159", "weight": 1.0}, {"source": "d_all_web_project_videoprotfoly_components_sections_aboutme_tsx", "target": "sections_aboutme_aboutmeprops", "relation": "contains", "confidence": "EXTRACTED", "source_file": "D:\\All Web project\\videoprotfoly\\components\\sections\\AboutMe.tsx", "source_location": "L161", "weight": 1.0}, {"source": "d_all_web_project_videoprotfoly_components_sections_aboutme_tsx", "target": "sections_aboutme_githubicon", "relation": "contains", "confidence": "EXTRACTED", "source_file": "D:\\All Web project\\videoprotfoly\\components\\sections\\AboutMe.tsx", "source_location": "L167", "weight": 1.0}, {"source": "d_all_web_project_videoprotfoly_components_sections_aboutme_tsx", "target": "sections_aboutme_linkedinicon", "relation": "contains", "confidence": "EXTRACTED", "source_file": "D:\\All Web project\\videoprotfoly\\components\\sections\\AboutMe.tsx", "source_location": "L181", "weight": 1.0}, {"source": "d_all_web_project_videoprotfoly_components_sections_aboutme_tsx", "target": "sections_aboutme_instagramicon", "relation": "contains", "confidence": "EXTRACTED", "source_file": "D:\\All Web project\\videoprotfoly\\components\\sections\\AboutMe.tsx", "source_location": "L197", "weight": 1.0}, {"source": "d_all_web_project_videoprotfoly_components_sections_aboutme_tsx", "target": "sections_aboutme_youtubeicon", "relation": "contains", "confidence": "EXTRACTED", "source_file": "D:\\All Web project\\videoprotfoly\\components\\sections\\AboutMe.tsx", "source_location": "L213", "weight": 1.0}, {"source": "d_all_web_project_videoprotfoly_components_sections_aboutme_tsx", "target": "sections_aboutme_aboutme", "relation": "contains", "confidence": "EXTRACTED", "source_file": "D:\\All Web project\\videoprotfoly\\components\\sections\\AboutMe.tsx", "source_location": "L228", "weight": 1.0}], "raw_calls": [{"caller_nid": "sections_aboutme_aboutme", "callee": "map", "is_member_call": true, "source_file": "D:\\All Web project\\videoprotfoly\\components\\sections\\AboutMe.tsx", "source_location": "L258"}, {"caller_nid": "sections_aboutme_aboutme", "callee": "split", "is_member_call": true, "source_file": "D:\\All Web project\\videoprotfoly\\components\\sections\\AboutMe.tsx", "source_location": "L301"}]}